{
  "INITIAL_Y": "0.605",
  "GROWTH_RATE": "2.047",
  "DECAY_RATE": "2.346",
  "BASELINE": "0.066",
  "WINTER_WEIGHT": "0.378",
  "AUTUMN_WEIGHT": "0.236",
  "WINTER_PEAK": "3.525",
  "AUTUMN_PEAK": "11.035",
  "AUTUMN_ONSET": "8.89",
  "AUTUMN_GATE_SHARPNESS": "4.63",
  "WINTER_WIDTH": "8.21",
  "WINTER_RISE_WIDTH": "7.846",
  "WINTER_FALL_WIDTH": "4.548",
  "AUTUMN_WIDTH": "7.064",
  "AUTUMN_RISE_WIDTH": "5.442",
  "AUTUMN_FALL_WIDTH": "7.883",
  "SUMMER_DIP": "0.15",
  "SUMMER_LOW": "8.79",
  "SUMMER_WIDTH": "7.58",
  "SUMMER_RISE_WIDTH": "7.308",
  "SUMMER_FALL_WIDTH": "7.484",
  "SCALE": "1.18",
  "SPECIES": "Song Thrush"
}
